agent_supervisor_memory/__init__.py
agent_supervisor_memory/cli.py
agent_supervisor_memory/config.py
agent_supervisor_memory/server.py
agent_supervisor_memory/services/__init__.py
agent_supervisor_memory/services/dispatch.py
agent_supervisor_memory/services/memory_store.py
agent_supervisor_memory/services/policy.py
agent_supervisor_memory/services/workflow_spec.py
agent_supervisor_memory/tools/__init__.py
agent_supervisor_memory/tools/core.py
agent_supervisor_memory/tools/dispatch.py
agent_supervisor_memory/tools/memory.py
agent_supervisor_memory/tools/projects.py
agent_supervisor_memory/tools/workflow.py
agent_supervisor_memory/utils/__init__.py
agent_supervisor_memory/utils/env.py
agent_supervisor_memory/utils/fs.py
agent_supervisor_memory/utils/metrics.py
agent_supervisor_memory/utils/ops_log.py
agent_supervisor_memory/utils/text.py
agent_supervisor_memory-0.2.41.dist-info/METADATA
agent_supervisor_memory-0.2.41.dist-info/WHEEL
agent_supervisor_memory-0.2.41.dist-info/entry_points.txt
agent_supervisor_memory-0.2.41.dist-info/licenses/LICENSE
agent_supervisor_memory-0.2.41.dist-info/RECORD
