Metadata-Version: 2.4
Name: agent-supervisor-memory
Version: 0.2.41
Summary: Local-first MCP tools: workflow routing/spec + keyword memory (JSON) with optional toggles.
License: MIT
License-File: LICENSE
Author: agent-supervisor-memory contributors
Requires-Python: >=3.10,<4.0
Classifier: License :: OSI Approved :: MIT License
Classifier: Programming Language :: Python :: 3
Classifier: Programming Language :: Python :: 3.10
Classifier: Programming Language :: Python :: 3.11
Classifier: Programming Language :: Python :: 3.12
Classifier: Programming Language :: Python :: 3.13
Classifier: Programming Language :: Python :: 3.14
Requires-Dist: mcp (==1.25.0)
Project-URL: Homepage, https://example.invalid/replace-me
